{"docs": [{"_id":"2020-11-04T08:23:48.573Z_4","template":"Seagoing_Personel","status":"Public","data":{"record_information":{"catalogue_id":"4","date_from":"2020-11-04","date_until":"2021-09-07T11:06:48","name":"Anna","surname":"Sydorenko","role_in_project":""},"source_identity":{"source_type_name":"","holder_organization_name":"","holder_organization_location":"","holder_organization_url":"","archive_name":"","inventory_number":"","type_of_document":"","title_of_book":"Алфавитный список служащих в Русском Обществе Пароходства и Торговли ","source_date_from":"1861","source_date_to_at":"","fonds_number":"","fonds_title":"","series_number":"","file_number":"","file_title":"","publisher_location":"","publisher_company":"","publisher_person_name":"","publisher_person_surname":"","publisher_year":"","overall_proffesion_status":"","company":"","note":"","comment":""},"employees_list":{"0":{"source_page":"2","person_name":"Д.","person_surname":"Акимов","person_fathers_name":"С.","service_in_company_profession":"Капитан","wage_type":"yearly","wage_value":"2694","wage_unit":"Рубль"},"1":{"source_page":"2","person_surname":"Артюхов","service_in_company_profession":"Помощник капитана","wage_type":"yearly","wage_value":"915","wage_unit":"Рубль","end_of_service_type":"end of service in company","end_of_service_reason":"Уволен"},"2":{"source_page":"2","person_surname":"Андреев","service_in_company_profession":"Капитан","wage_type":"yearly","wage_value":"1400","wage_unit":"Рубль"},"3":{"source_page":"2","person_surname":"Андрусов","service_in_company_profession":"Помощник капитана","wage_type":"yearly","wage_value":"603","wage_unit":"Рубль"},"4":{"source_page":"2","person_surname":"Абакшин","service_in_company_profession":"Помощник капитана","wage_type":"yearly","wage_value":"537","wage_unit":"Рубль"},"5":{"source_page":"2","person_surname":"Астус","service_in_company_profession":"Механик","wage_type":"yearly","wage_value":"1227","wage_unit":"Рубль"},"6":{"source_page":"2","person_surname":"Агафонов","service_in_company_profession":"Помощник капитана","wage_type":"yearly","wage_value":"1012","wage_unit":"Рубль"},"7":{"source_page":"2","person_surname":"Акулов","service_in_company_profession":"Капитан","wage_type":"yearly","wage_value":"2366","wage_unit":"Рубль"},"8":{"source_page":"2","person_surname":"Анов","service_in_company_profession":"Помощник капитана","wage_type":"yearly","wage_value":"516","wage_unit":"Рубль"},"9":{"source_page":"2","person_surname":"Арно","service_in_company_profession":"Механик","wage_type":"yearly","wage_value":"678","wage_unit":"Рубль","end_of_service_type":"end of service in company","end_of_service_reason":"Уволен"},"10":{"source_page":"2","person_name":"В.","person_surname":"Акимов","person_fathers_name":"С.","service_in_company_profession":"Помощник капитана","wage_type":"yearly","wage_value":"1221","wage_unit":"Рубль"},"11":{"source_page":"2","person_surname":"Алиман","service_in_company_profession":"Помощник капитана","wage_type":"yearly","wage_value":"1556","wage_unit":"Рубль"},"12":{"source_page":"2","person_name":"С.","person_surname":"Алексеев","service_in_company_profession":"Механик","wage_type":"yearly","wage_value":"718","wage_unit":"Рубль"},"13":{"source_page":"2","person_surname":"Атанаскович","service_in_company_profession":"Помощник капитана","wage_type":"yearly","wage_value":"735","wage_unit":"Рубль"},"14":{"source_page":"2","person_surname":"Абрамович","service_in_company_profession":"Помощник капитана","wage_type":"yearly","wage_value":"236","wage_unit":"Рубль","end_of_service_type":"end of service in company","end_of_service_reason":"Уволен"},"15":{"source_page":"2","person_surname":"Беляев","service_in_company_profession":"Механик","wage_type":"yearly","wage_value":"1650","wage_unit":"Рубль"},"16":{"source_page":"2","person_surname":"Барбариго","service_in_company_profession":"Механик","wage_type":"yearly","wage_value":"1663","wage_unit":"Рубль"},"17":{"source_page":"2","person_surname":"Борт","service_in_company_profession":"Механик","wage_type":"yearly","wage_value":"2107","wage_unit":"Рубль"},"18":{"source_page":"2","person_name":"Ф.","person_surname":"Бернацкий","service_in_company_profession":"Капитан","wage_type":"yearly","wage_value":"2500","wage_unit":"Рубль"},"19":{"source_page":"2","person_surname":"Будяченко","service_in_company_profession":"Механик ученик","wage_type":"yearly","wage_value":"133","wage_unit":"Рубль"},"20":{"source_page":"2","person_name":"В.","person_surname":"Богданович","service_in_company_profession":"Капитан","wage_type":"yearly","wage_value":"1774","wage_unit":"Рубль"},"21":{"source_page":"2","person_surname":"Богненко","service_in_company_profession":"Помощник капитана","wage_type":"yearly","wage_value":"593","wage_unit":"Рубль"},"22":{"source_page":"2","person_name":"Ф.","person_surname":"Бернардо","service_in_company_profession":"Механик","wage_type":"yearly","wage_value":"1726","wage_unit":"Рубль"},"23":{"source_page":"2","person_surname":"Бринк","service_in_company_profession":"Механик","wage_type":"yearly","wage_value":"1080","wage_unit":"Рубль","end_of_service_type":"end of service in company","end_of_service_reason":"Уволен"},"24":{"source_page":"2","person_name":"А.","person_surname":"Бринкстон","service_in_company_profession":"Механик","wage_type":"yearly","wage_value":"867","wage_unit":"Рубль"},"25":{"source_page":"2","person_name":"И.","person_surname":"Божеданов","service_in_company_profession":"Помощник капитана по грузовой части","wage_type":"yearly","wage_value":"600","wage_unit":"Рубль"},"26":{"source_page":"4","person_surname":"Басов","service_in_company_profession":"Механик","wage_type":"yearly","wage_value":"1340","wage_unit":"Рубль"},"27":{"source_page":"4","person_surname":"Буврет","service_in_company_profession":"Механик","wage_type":"yearly","wage_value":"1880","wage_unit":"Рубль"},"28":{"source_page":"4","person_name":"Н.","person_surname":"Баранов","service_in_company_profession":"Помощник капитана","wage_type":"yearly","wage_value":"933","wage_unit":"Рубль"},"29":{"source_page":"4","person_surname":"Брюн","service_in_company_profession":"Лоцман","wage_type":"yearly","wage_value":"197","wage_unit":"Рубль"},"30":{"source_page":"4","person_surname":"Бравачич","service_in_company_profession":"Помощник капитана","wage_type":"yearly","wage_value":"1104","wage_unit":"Рубль"},"31":{"source_page":"4","person_name":"Ж.","person_surname":"Будо","person_fathers_name":"Б.","service_in_company_profession":"Механик","wage_type":"yearly","wage_value":"1558","wage_unit":"Рубль"},"32":{"source_page":"4","person_name":"Ж.","person_surname":"Бенард","service_in_company_profession":"Механик","wage_type":"yearly","wage_value":"1556","wage_unit":"Рубль"},"33":{"source_page":"4","person_surname":"Быстряков","service_in_company_profession":"Механический ученик","wage_type":"yearly","wage_value":"304","wage_unit":"Рубль"},"34":{"source_page":"4","person_surname":"Белюков","service_in_company_profession":"Механик","wage_type":"yearly","wage_value":"1330","wage_unit":"Рубль"},"35":{"source_page":"4","person_name":"А.","person_surname":"Браисон","service_in_company_profession":"Механик","wage_type":"yearly","wage_value":"660","wage_unit":"Рубль"},"36":{"source_page":"4","person_surname":"Бен","service_in_company_profession":"Механик","wage_type":"yearly","wage_value":"1329","wage_unit":"Рубль"},"37":{"source_page":"4","person_name":"Я.","person_surname":"Беннардо","service_in_company_profession":"Механик","wage_type":"yearly","wage_value":"716","wage_unit":"Рубль"},"38":{"source_page":"4","person_name":"М.","person_surname":"Бальохин","service_in_company_profession":"Капитан","wage_type":"yearly","wage_value":"945","wage_unit":"Рубль"},"39":{"source_page":"4","person_surname":"Брунстронг","service_in_company_profession":"Механик","wage_type":"yearly","wage_value":"1520","wage_unit":"Рубль"},"40":{"source_page":"4","person_name":"Г.","person_surname":"Бон","service_in_company_profession":"Механик","wage_type":"yearly","wage_value":"501","wage_unit":"Рубль"},"41":{"source_page":"4","person_surname":"Боурес","service_in_company_profession":"Механик","wage_type":"yearly","wage_value":"644","wage_unit":"Рубль"},"42":{"source_page":"4","person_surname":"Витвицкий","service_in_company_profession":"Капитан","wage_type":"yearly","wage_value":"1660","wage_unit":"Рубль"},"43":{"source_page":"4","person_name":"И.","person_surname":"Вальховский","service_in_company_profession":"Капитан","wage_type":"yearly","wage_value":"1603","wage_unit":"Рубль"},"44":{"source_page":"4","person_surname":"Воронков","service_in_company_profession":"Помощник капитана","wage_type":"yearly","wage_value":"54","wage_unit":"Рубль"},"45":{"source_page":"4","person_name":"П.","person_surname":"Вальховский","service_in_company_profession":"Механический ученик","wage_type":"yearly","wage_value":"488","wage_unit":"Рубль"},"46":{"source_page":"4","person_name":"П.","person_surname":"Витт","service_in_company_profession":"Помощник капитана","wage_type":"yearly","wage_value":"747","wage_unit":"Рубль"},"47":{"source_page":"4","person_surname":"Ваймер","service_in_company_profession":"Механик","wage_type":"yearly","wage_value":"1559","wage_unit":"Рубль"},"48":{"source_page":"4","person_name":"Н.","person_surname":"Витт","service_in_company_profession":"Помощник капитана","wage_type":"yearly","wage_value":"1563","wage_unit":"Рубль"},"49":{"source_page":"6","person_surname":"Васало","service_in_company_profession":"Помощник капитана","wage_type":"yearly","wage_value":"103","wage_unit":"Рубль"},"50":{"source_page":"6","person_surname":"Вранцов","service_in_company_profession":"Помощник капитана","wage_type":"yearly","wage_value":"1600","wage_unit":"Рубль"},"51":{"source_page":"6","person_surname":"Вильсон","service_in_company_profession":"Механик","wage_type":"yearly","wage_value":"1756","wage_unit":"Рубль"},"52":{"source_page":"6","person_surname":"Викгорст","service_in_company_profession":"Помощник капитана","wage_type":"yearly","wage_value":"1569","wage_unit":"Рубль"},"53":{"source_page":"6","person_surname":"Вуд","service_in_company_profession":"Механик","wage_type":"yearly","wage_value":"1741","wage_unit":"Рубль"},"54":{"source_page":"6","person_surname":"Валлас","service_in_company_profession":"Механик","wage_type":"yearly","wage_value":"1095","wage_unit":"Рубль"},"55":{"source_page":"6","person_surname":"Видаль","service_in_company_profession":"Механик","wage_type":"yearly","wage_value":"1024","wage_unit":"Рубль"},"56":{"source_page":"6","person_surname":"Волохов","service_in_company_profession":"Механический ученик","wage_type":"yearly","wage_value":"148","wage_unit":"Рубль"},"57":{"source_page":"6","person_surname":"Вильд","service_in_company_profession":"Механик","wage_type":"yearly","wage_value":"850","wage_unit":"Рубль"},"58":{"source_page":"6","person_surname":"Винк","service_in_company_profession":"Капитан","wage_type":"yearly","wage_value":"805","wage_unit":"Рубль"},"59":{"source_page":"6","person_surname":"Вильям","service_in_company_profession":"Механик","wage_type":"yearly","wage_value":"290","wage_unit":"Рубль"},"60":{"source_page":"6","person_surname":"Голенищев","service_in_company_profession":"Капитан","wage_type":"yearly","wage_value":"1988","wage_unit":"Рубль"},"61":{"source_page":"6","person_surname":"Гоес","service_in_company_profession":"Капитан","wage_type":"yearly","wage_value":"2292","wage_unit":"Рубль"},"62":{"source_page":"6","person_surname":"Гаврилюк","service_in_company_profession":"Помощник капитана","wage_type":"yearly","wage_value":"1109","wage_unit":"Рубль"},"63":{"source_page":"6","person_surname":"Гейкинг","service_in_company_profession":"Капитан","wage_type":"yearly","wage_value":"2353","wage_unit":"Рубль"},"64":{"source_page":"6","person_name":"В.","person_surname":"Грегам","service_in_company_profession":"Механик","wage_type":"yearly","wage_value":"660","wage_unit":"Рубль"},"65":{"source_page":"6","person_surname":"Голенко","service_in_company_profession":"Капитан","wage_type":"yearly","wage_value":"1979","wage_unit":"Рубль"},"66":{"source_page":"6","person_name":"М.","person_surname":"Герасимов","service_in_company_profession":"Механический ученик","wage_type":"yearly","wage_value":"685","wage_unit":"Рубль"},"67":{"source_page":"6","person_surname":"Гибсон","service_in_company_profession":"Механик","wage_type":"yearly","wage_value":"1129","wage_unit":"Рубль"},"68":{"source_page":"6","person_surname":"Горголи","service_in_company_profession":"Помощник капитана","wage_type":"yearly","wage_value":"1600","wage_unit":"Рубль"},"69":{"source_page":"6","person_name":"А.","person_surname":"Греве","service_in_company_profession":"Капитан","wage_type":"yearly","wage_value":"3497","wage_unit":"Рубль"},"70":{"source_page":"6","person_name":"И.","person_surname":"Гавришев","service_in_company_profession":"Помощник капитана","wage_type":"yearly","wage_value":"266","wage_unit":"Рубль"},"71":{"source_page":"6","person_surname":"Гилеспи","service_in_company_profession":"Механик","wage_type":"yearly","wage_value":"1902","wage_unit":"Рубль"},"72":{"source_page":"6","person_surname":"Грищенко","service_in_company_profession":"Штурманский ученик","wage_type":"yearly","wage_value":"269","wage_unit":"Рубль"},"73":{"source_page":"6","person_surname":"Гербст","service_in_company_profession":"Механик","wage_type":"yearly","wage_value":"1841","wage_unit":"Рубль"},"74":{"source_page":"8","person_surname":"Грекке","service_in_company_profession":"Помощник капитана","wage_type":"yearly","wage_value":"1596","wage_unit":"Рубль"},"75":{"source_page":"8","person_surname":"Греблен","service_in_company_profession":"Механик","wage_type":"yearly","wage_value":"898","wage_unit":"Рубль"},"76":{"source_page":"8","person_surname":"Гюм","service_in_company_profession":"Механик","wage_type":"yearly","wage_value":"1099","wage_unit":"Рубль"},"77":{"source_page":"8","person_surname":"Гюбнер","service_in_company_profession":"Механик","wage_type":"yearly","wage_value":"400","wage_unit":"Рубль"},"78":{"source_page":"8","person_surname":"Горн","service_in_company_profession":"Механик","wage_type":"yearly","wage_value":"1889","wage_unit":"Рубль"},"79":{"source_page":"8","person_surname":"Григорьев","service_in_company_profession":"Помощник капитана","wage_type":"yearly","wage_value":"740","wage_unit":"Рубль"},"80":{"source_page":"8","person_surname":"Горслей-Керберт","service_in_company_profession":"Механик","wage_type":"yearly","wage_value":"1388","wage_unit":"Рубль"},"81":{"source_page":"8","person_surname":"Гопчевич","service_in_company_profession":"Помощник капитана","wage_type":"yearly","wage_value":"375","wage_unit":"Рубль"},"82":{"source_page":"8","person_name":"Л.","person_surname":"Гавришев","service_in_company_profession":"Помощиник капитана","wage_type":"yearly","wage_value":"664","wage_unit":"Рубль"},"83":{"source_page":"8","person_surname":"Гайтани","service_in_company_profession":"Помощник капитана","wage_type":"yearly","wage_value":"166","wage_unit":"Рубль"},"84":{"source_page":"8","person_name":"Я.","person_surname":"Дурнев","service_in_company_profession":"Капитан","wage_type":"yearly","wage_value":"2115","wage_unit":"Рубль"},"85":{"source_page":"8","person_name":"Ф.","person_surname":"Давидов","service_in_company_profession":"Капитан","wage_type":"yearly","wage_value":"2105","wage_unit":"Рубль"},"86":{"source_page":"8","person_surname":"Дмитриев","service_in_company_profession":"Капитан","wage_type":"yearly","wage_value":"1600","wage_unit":"Рубль"},"87":{"source_page":"8","person_surname":"Диденкулов","service_in_company_profession":"Механический ученик","wage_type":"yearly","wage_value":"384","wage_unit":"Рубль"},"88":{"source_page":"8","person_surname":"Демме","service_in_company_profession":"Помощник капитана","wage_type":"yearly","wage_value":"800","wage_unit":"Рубль"},"89":{"source_page":"8","person_name":"Л.","person_surname":"Ди-Виен","service_in_company_profession":"Капитан","wage_type":"yearly","wage_value":"2160","wage_unit":"Рубль"},"90":{"source_page":"8","person_surname":"Долганов","service_in_company_profession":"Помощник капитана","wage_type":"yearly","wage_value":"937","wage_unit":"Рубль"},"91":{"source_page":"8","person_surname":"Дубинин","service_in_company_profession":"Помощник капитана","wage_type":"yearly","wage_value":"760","wage_unit":"Рубль"},"92":{"source_page":"8","person_surname":"Дробот","service_in_company_profession":"Помощник капитана","wage_type":"yearly","wage_value":"525","wage_unit":"Рубль"},"93":{"source_page":"10","person_surname":"Джуркевич","service_in_company_profession":"Помощник капитана","wage_type":"yearly","wage_value":"1053","wage_unit":"Рубль"},"94":{"source_page":"10","person_surname":"Дабчевич","service_in_company_profession":"Помощник капитана","wage_type":"yearly","wage_value":"509","wage_unit":"Рубль"},"95":{"source_page":"10","person_surname":"Донольд","service_in_company_profession":"Механик","wage_type":"yearly","wage_value":"400","wage_unit":"Рубль"},"96":{"source_page":"10","person_surname":"Дин","service_in_company_profession":"Механик","wage_type":"yearly","wage_value":"400","wage_unit":"Рубль"},"97":{"source_page":"10","person_surname":"Драгоманович","service_in_company_profession":"Помощник капитана","wage_type":"yearly","wage_value":"167","wage_unit":"Рубль"},"98":{"source_page":"10","person_surname":"Егоров","service_in_company_profession":"Механический ученик","wage_type":"yearly","wage_value":"94","wage_unit":"Рубль"},"99":{"source_page":"10","person_surname":"Ефремов","service_in_company_profession":"Механический ученик","wage_type":"yearly","wage_value":"250","wage_unit":"Рубль"},"100":{"source_page":"10","person_surname":"Есаулов","service_in_company_profession":"Капитан","wage_type":"yearly","wage_value":"1636","wage_unit":"Рубль"},"101":{"source_page":"10","person_name":"А.","person_surname":"Жуков","service_in_company_profession":"Помощник капитана","wage_type":"yearly","wage_value":"720","wage_unit":"Рубль"},"102":{"source_page":"10","person_surname":"Жреве","service_in_company_profession":"Помощник капитана","wage_type":"yearly","wage_value":"1333","wage_unit":"Рубль"},"103":{"source_page":"10","person_surname":"Жирард","service_in_company_profession":"Помощник капитана","wage_type":"yearly","wage_value":"1205","wage_unit":"Рубль"},"104":{"source_page":"10","person_surname":"Жилли","service_in_company_profession":"Механик","wage_type":"yearly","wage_value":"823","wage_unit":"Рубль"},"105":{"source_page":"10","person_surname":"Зелененко","service_in_company_profession":"Механический ученик","wage_type":"yearly","wage_value":"378","wage_unit":"Рубль"},"106":{"source_page":"10","person_surname":"Заболотный","service_in_company_profession":"Капитан","wage_type":"yearly","wage_value":"2725","wage_unit":"Рубль"},"107":{"source_page":"10","person_surname":"Залетаев","service_in_company_profession":"Помощник капитана","wage_type":"yearly","wage_value":"333","wage_unit":"Рубль"},"108":{"source_page":"10","person_surname":"Зибелич","service_in_company_profession":"Помощник капитана","wage_type":"yearly","wage_value":"1013","wage_unit":"Рубль"},"109":{"source_page":"10","person_name":"П.","person_surname":"Зубков","service_in_company_profession":"Помощник капитана","wage_type":"yearly","wage_value":"583","wage_unit":"Рубль"},"110":{"source_page":"10","person_surname":"Зельно","service_in_company_profession":"Механик","wage_type":"yearly","wage_value":"801","wage_unit":"Рубль"},"111":{"source_page":"10","person_name":"Ефим","person_surname":"Иванов","service_in_company_profession":"Капитан","wage_type":"yearly","wage_value":"2237","wage_unit":"Рубль"},"112":{"source_page":"10","person_name":"Егор","person_surname":"Иванов","service_in_company_profession":"Помощник капитана","wage_type":"yearly","wage_value":"1600","wage_unit":"Рубль"},"113":{"source_page":"10","person_name":"П.","person_surname":"Иванов","service_in_company_profession":"Капитан","wage_type":"yearly","wage_value":"853","wage_unit":"Рубль"},"114":{"source_page":"10","person_name":"А.","person_surname":"Иованович","service_in_company_profession":"Помощник капитана","wage_type":"yearly","wage_value":"982","wage_unit":"Рубль"},"115":{"source_page":"10","person_name":"В.","person_surname":"Инглези","service_in_company_profession":"Помощник капитана","wage_type":"yearly","wage_value":"245","wage_unit":"Рубль"},"116":{"source_page":"10","person_name":"И.","person_surname":"Иванс","service_in_company_profession":"Механик","wage_type":"yearly","wage_value":"1299","wage_unit":"Рубль"},"117":{"source_page":"12","person_name":"Н.","person_surname":"Карпов","service_in_company_profession":"Механический ученик","wage_type":"yearly","wage_value":"179","wage_unit":"Рубль"},"118":{"source_page":"12","person_name":"М.","person_surname":"Коханский","service_in_company_profession":"Механический ученик","wage_type":"yearly","wage_value":"348","wage_unit":"Рубль"},"119":{"source_page":"12","person_name":"Д.","person_surname":"Кей","service_in_company_profession":"Механик","wage_type":"yearly","wage_value":"1110","wage_unit":"Рубль"},"120":{"source_page":"12","person_name":"М.","person_surname":"Кази","service_in_company_profession":"Помощник капитана","wage_type":"yearly","wage_value":"1336","wage_unit":"Рубль"},"121":{"source_page":"12","person_name":"И.","person_surname":"Коперницкий","service_in_company_profession":"Капитан","wage_type":"yearly","wage_value":"2276","wage_unit":"Рубль"},"122":{"source_page":"12","person_name":"В.","person_surname":"Кирьяков","service_in_company_profession":"Капитан","wage_type":"yearly","wage_value":"1125","wage_unit":"Рубль"},"123":{"source_page":"12","person_name":"Н.","person_surname":"Каменщиков","service_in_company_profession":"Механический ученик","wage_type":"yearly","wage_value":"559","wage_unit":"Рубль"},"124":{"source_page":"12","person_name":"К.","person_surname":"Кисилевич","service_in_company_profession":"Помощник капитана","wage_type":"yearly","wage_value":"854","wage_unit":"Рубль"},"125":{"source_page":"12","person_name":"Э.","person_surname":"Кнаст","service_in_company_profession":"Механик","wage_type":"yearly","wage_value":"575","wage_unit":"Рубль"},"126":{"source_page":"12","person_surname":"Кеннеди","service_in_company_profession":"Механик","wage_type":"yearly","wage_value":"1540","wage_unit":"Рубль"},"127":{"source_page":"12","person_surname":"Красноштанов","service_in_company_profession":"Механик","wage_type":"yearly","wage_value":"50","wage_unit":"Рубль"},"128":{"source_page":"12","person_surname":"Комаровский","service_in_company_profession":"Капитан","wage_type":"yearly","wage_value":"2055","wage_unit":"Рубль"},"129":{"source_page":"12","person_surname":"Коксон","service_in_company_profession":"Механик","wage_type":"yearly","wage_value":"1780","wage_unit":"Рубль"},"130":{"source_page":"12","person_surname":"Кольдуэль","service_in_company_profession":"Механик","wage_type":"yearly","wage_value":"340","wage_unit":"Рубль"},"131":{"source_page":"12","person_surname":"Климов","service_in_company_profession":"Механик","wage_type":"yearly","wage_value":"1592","wage_unit":"Рубль"},"132":{"source_page":"12","person_surname":"Кутизонди","service_in_company_profession":"Лоцман","wage_type":"yearly","wage_value":"900","wage_unit":"Рубль"},"133":{"source_page":"12","person_surname":"Кушныренко","service_in_company_profession":"Капитан","wage_type":"yearly","wage_value":"2012","wage_unit":"Рубль"},"134":{"source_page":"12","person_surname":"Коперницкий","service_in_company_profession":"Капитан","wage_type":"yearly","wage_value":"1967","wage_unit":"Рубль"},"135":{"source_page":"12","person_surname":"Курганов","service_in_company_profession":"Помощник капитана","wage_type":"yearly","wage_value":"1400","wage_unit":"Рубль"},"136":{"source_page":"12","person_name":"Я.","person_surname":"Кренстон","service_in_company_profession":"Механик","wage_type":"yearly","wage_value":"1428","wage_unit":"Рубль"},"137":{"source_page":"12","person_name":"Л.","person_surname":"Козлов","service_in_company_profession":"Помощник капитана","wage_type":"yearly","wage_value":"331","wage_unit":"Рубль"},"138":{"source_page":"14","person_name":"Ф.","person_surname":"Крюс","service_in_company_profession":"Механик","wage_type":"yearly","wage_value":"1046","wage_unit":"Рубль"},"139":{"source_page":"14","person_surname":"Кюнеман","service_in_company_profession":"Помощник капитана","wage_type":"yearly","wage_value":"600","wage_unit":"Рубль"},"140":{"source_page":"14","person_name":"Ф.","person_surname":"Красиков","service_in_company_profession":"Механик","wage_type":"yearly","wage_value":"840","wage_unit":"Рубль"},"141":{"source_page":"14","person_name":"Д.","person_surname":"Кембель","service_in_company_profession":"Механик","wage_type":"yearly","wage_value":"1177","wage_unit":"Рубль"},"142":{"source_page":"14","person_name":"Х.","person_surname":"Кисилевич","service_in_company_profession":"Механический ученик","wage_type":"yearly","wage_value":"174","wage_unit":"Рубль"},"143":{"source_page":"14","person_name":"Р.","person_surname":"Локерт","service_in_company_profession":"Механик","wage_type":"yearly","wage_value":"1930","wage_unit":"Рубль"},"144":{"source_page":"14","person_name":"С.","person_surname":"Лазаревич","service_in_company_profession":"Механик","wage_type":"yearly","wage_value":"510","wage_unit":"Рубль"},"145":{"source_page":"14","person_surname":"Летвер","service_in_company_profession":"Механик","wage_type":"yearly","wage_value":"483","wage_unit":"Рубль"},"146":{"source_page":"14","person_surname":"Лингардт","service_in_company_profession":"Механик","wage_type":"yearly","wage_value":"1080","wage_unit":"Рубль"},"147":{"source_page":"14","person_surname":"Лазарев","service_in_company_profession":"Механик","wage_type":"yearly","wage_value":"50","wage_unit":"Рубль"},"148":{"source_page":"14","person_surname":"Ларош","service_in_company_profession":"Механик","wage_type":"yearly","wage_value":"2075","wage_unit":"Рубль"},"149":{"source_page":"14","person_name":"С.","person_surname":"Лазаревич","service_in_company_profession":"Капитан","wage_type":"yearly","wage_value":"2327","wage_unit":"Рубль"},"150":{"source_page":"14","person_surname":"Лаутон","service_in_company_profession":"Механик","wage_type":"yearly","wage_value":"3697","wage_unit":"Рубль"},"151":{"source_page":"14","person_name":"С.","person_surname":"Леонов","service_in_company_profession":"Механик","wage_type":"yearly","wage_value":"497","wage_unit":"Рубль"},"152":{"source_page":"14","person_name":"А.","person_surname":"Маркаков","service_in_company_profession":"Помощник капитана","wage_type":"yearly","wage_value":"861","wage_unit":"Рубль"},"153":{"source_page":"14","person_name":"М.","person_surname":"Мелихов","service_in_company_profession":"Капитан","wage_type":"yearly","wage_value":"1959","wage_unit":"Рубль"},"154":{"source_page":"14","person_name":"П.","person_surname":"Максутов","person_fathers_name":"К.","service_in_company_profession":"Капитан","wage_type":"yearly","wage_value":"2296","wage_unit":"Рубль"},"155":{"source_page":"14","person_name":"Н.","person_surname":"Магаринский","service_in_company_profession":"Помощник капитана","wage_type":"yearly","wage_value":"1237","wage_unit":"Рубль"},"156":{"source_page":"14","person_name":"И.","person_surname":"Мунтьянов","service_in_company_profession":"Капитан","wage_type":"yearly","wage_value":"1379","wage_unit":"Рубль"},"157":{"source_page":"14","person_name":"С.","person_surname":"Мармусевич","service_in_company_profession":"Помощник капитана","wage_type":"yearly","wage_value":"451","wage_unit":"Рубль"},"158":{"source_page":"14","person_name":"Ф.","person_surname":"Массей","service_in_company_profession":"Главный механик","wage_type":"yearly","wage_value":"1666","wage_unit":"Рубль"},"159":{"source_page":"16","person_name":"В.","person_surname":"Милевич","service_in_company_profession":"Лоцман","wage_type":"yearly","wage_value":"900","wage_unit":"Рубль"},"160":{"source_page":"16","person_name":"Н.","person_surname":"Милонас","service_in_company_profession":"Капитан","wage_type":"yearly","wage_value":"2343","wage_unit":"Рубль"},"161":{"source_page":"16","person_name":"И.","person_surname":"Масленников","service_in_company_profession":"Помощник капитана","wage_type":"yearly","wage_value":"208","wage_unit":"Рубль"},"162":{"source_page":"16","person_surname":"Матюшкин","service_in_company_profession":"Помощник капитана","wage_type":"yearly","wage_value":"1265","wage_unit":"Рубль"},"163":{"source_page":"16","person_surname":"Мелетин","service_in_company_profession":"Помощник капитана","wage_type":"yearly","wage_value":"1605","wage_unit":"Рубль"},"164":{"source_page":"16","person_name":"Г.","person_surname":"Маккей","service_in_company_profession":"Механик","wage_type":"yearly","wage_value":"748","wage_unit":"Рубль"},"165":{"source_page":"16","person_name":"Р.","person_surname":"Мерфи","service_in_company_profession":"Механик","wage_type":"yearly","wage_value":"1186","wage_unit":"Рубль"},"166":{"source_page":"16","person_name":"И.","person_surname":"Невражин","service_in_company_profession":"Помощник капитана","wage_type":"yearly","wage_value":"1566","wage_unit":"Рубль"},"167":{"source_page":"16","person_name":"А.","person_surname":"Навроцкий","service_in_company_profession":"Помощник капитана","wage_type":"yearly","wage_value":"1195","wage_unit":"Рубль"},"168":{"source_page":"16","person_name":"П.","person_surname":"Норов","service_in_company_profession":"Механик ученик","wage_type":"yearly","wage_value":"208","wage_unit":"Рубль"},"169":{"source_page":"16","person_surname":"Недомолвин","service_in_company_profession":"Помощник капитана","wage_type":"yearly","wage_value":"300","wage_unit":"Рубль"},"170":{"source_page":"16","person_surname":"Нилов","service_in_company_profession":"Помощник капитана","wage_type":"yearly","wage_value":"1400","wage_unit":"Рубль"},"171":{"source_page":"16","person_name":"В.","person_surname":"Невинс","service_in_company_profession":"Механик","wage_type":"yearly","wage_value":"1734","wage_unit":"Рубль"},"172":{"source_page":"16","person_name":"Т.","person_surname":"Нерни","service_in_company_profession":"Механик","wage_type":"yearly","wage_value":"420","wage_unit":"Рубль"},"173":{"source_page":"16","person_name":"В.","person_surname":"Овен","service_in_company_profession":"Механик","wage_type":"yearly","wage_value":"2000","wage_unit":"Рубль"},"174":{"source_page":"16","person_name":"Адольф","person_surname":"Овен","service_in_company_profession":"Механик","wage_type":"yearly","wage_value":"857","wage_unit":"Рубль"},"175":{"source_page":"18","person_name":"Август","person_surname":"Овен","service_in_company_profession":"Механик","wage_type":"yearly","wage_value":"1080","wage_unit":"Рубль"},"176":{"source_page":"18","person_name":"К.","person_surname":"Овденко","service_in_company_profession":"Механический ученик","wage_type":"yearly","wage_value":"204","wage_unit":"Рубль"},"177":{"source_page":"18","person_name":"И.","person_surname":"Общий","service_in_company_profession":"Механик","wage_type":"yearly","wage_value":"840","wage_unit":"Рубль"},"178":{"source_page":"18","person_name":"Д.","person_surname":"Орр","service_in_company_profession":"Механик","wage_type":"yearly","wage_value":"1195","wage_unit":"Рубль"},"179":{"source_page":"18","person_name":"Г.","person_surname":"Петров","service_in_company_profession":"Механик","wage_type":"yearly","wage_value":"1832","wage_unit":"Рубль"},"180":{"source_page":"18","person_name":"П.","person_surname":"Прохоров","service_in_company_profession":"Механик","wage_type":"yearly","wage_value":"1236","wage_unit":"Рубль"},"181":{"source_page":"18","person_name":"С.","person_surname":"Певнев","service_in_company_profession":"Помощник капитана","wage_type":"yearly","wage_value":"854","wage_unit":"Рубль"},"182":{"source_page":"18","person_name":"Ф.","person_surname":"Птицын","service_in_company_profession":"Механик","wage_type":"yearly","wage_value":"1558","wage_unit":"Рубль"},"183":{"source_page":"18","person_name":"Н.","person_surname":"Прокопович","service_in_company_profession":"Капитан","wage_type":"yearly","wage_value":"1693","wage_unit":"Рубль"},"184":{"source_page":"18","person_name":"И.","person_surname":"Поляков","service_in_company_profession":"Механический ученик","wage_type":"yearly","wage_value":"203","wage_unit":"Рубль"},"185":{"source_page":"18","person_name":"Д.","person_surname":"Пата-Егоров","service_in_company_profession":"Капитан","wage_type":"yearly","wage_value":"2416","wage_unit":"Рубль"},"186":{"source_page":"18","person_name":"Е.","person_surname":"Папков","service_in_company_profession":"Помощник капитана","wage_type":"yearly","wage_value":"972","wage_unit":"Рубль"},"187":{"source_page":"18","person_name":"П.","person_surname":"Пошивальников","service_in_company_profession":"Механический ученик","wage_type":"yearly","wage_value":"165","wage_unit":"Рубль"},"188":{"source_page":"18","person_name":"М.","person_surname":"Политов","service_in_company_profession":"Помощник капитана","wage_type":"yearly","wage_value":"630","wage_unit":"Рубль"},"189":{"source_page":"18","person_surname":"Пальмен","service_in_company_profession":"Машинист","wage_type":"yearly","wage_value":"185","wage_unit":"Рубль"},"190":{"source_page":"18","person_name":"В.","person_surname":"Петерс","service_in_company_profession":"Механик","wage_type":"yearly","wage_value":"1400","wage_unit":"Рубль"},"191":{"source_page":"18","person_name":"И.","person_surname":"Попович","service_in_company_profession":"Капитан","wage_type":"yearly","wage_value":"925","wage_unit":"Рубль"},"192":{"source_page":"18","person_name":"К.","person_surname":"Периалов","service_in_company_profession":"Помощник капитана","wage_type":"yearly","wage_value":"937","wage_unit":"Рубль"},"193":{"source_page":"18","person_name":"Г.","person_surname":"Петров","service_in_company_profession":"Механик","wage_type":"yearly","wage_value":"1563","wage_unit":"Рубль"},"194":{"source_page":"18","person_name":"М.","person_surname":"Павловский","service_in_company_profession":"Механический ученик","wage_type":"yearly","wage_value":"122","wage_unit":"Рубль"},"195":{"source_page":"18","person_name":"В.","person_surname":"Павленко","service_in_company_profession":"Механический ученик","wage_type":"yearly","wage_value":"75","wage_unit":"Рубль"},"196":{"source_page":"18","person_surname":"Петкович","service_in_company_profession":"Помощник капитана","wage_type":"yearly","wage_value":"1371","wage_unit":"Рубль"},"197":{"source_page":"18","person_name":"Р.","person_surname":"Петерсон","service_in_company_profession":"Механик","wage_type":"yearly","wage_value":"1431","wage_unit":"Рубль"},"198":{"source_page":"18","person_surname":"Портнов","service_in_company_profession":"Механик","wage_type":"yearly","wage_value":"1734","wage_unit":"Рубль"},"199":{"source_page":"18","person_name":"В.","person_surname":"Петерсон","person_fathers_name":"Э.","service_in_company_profession":"Механик","wage_type":"yearly","wage_value":"1514","wage_unit":"Рубль"},"200":{"source_page":"20","person_name":"И.","person_surname":"Пулич","service_in_company_profession":"Помощник капитана","wage_type":"yearly","wage_value":"575","wage_unit":"Рубль"},"201":{"source_page":"20","person_name":"С.","person_surname":"Павлович","service_in_company_profession":"Помощник капитана","wage_type":"yearly","wage_value":"1043","wage_unit":"Рубль"},"202":{"source_page":"20","person_name":"Я.","person_surname":"Поль","service_in_company_profession":"Механик","wage_type":"yearly","wage_value":"1741","wage_unit":"Рубль"},"203":{"source_page":"20","person_name":"К.","person_surname":"Плотников","service_in_company_profession":"Механик","wage_type":"yearly","wage_value":"855","wage_unit":"Рубль"},"204":{"source_page":"20","person_name":"Д.","person_surname":"Попадато","service_in_company_profession":"Лоцман","wage_type":"yearly","wage_value":"20","wage_unit":"Рубль"},"205":{"source_page":"20","person_name":"А.","person_surname":"Попович","service_in_company_profession":"Механический ученик","wage_type":"yearly","wage_value":"153","wage_unit":"Рубль"},"206":{"source_page":"20","person_surname":"Повало-Швейковский","service_in_company_profession":"Капитан","wage_type":"yearly","wage_value":"1170","wage_unit":"Рубль"},"207":{"source_page":"20","person_name":"И.","person_surname":"Понс","service_in_company_profession":"Механик","wage_type":"yearly","wage_value":"140","wage_unit":"Рубль"},"208":{"source_page":"20","person_name":"Г.","person_surname":"Поль","service_in_company_profession":"Механик","wage_type":"yearly","wage_value":"503","wage_unit":"Рубль"},"209":{"source_page":"20","person_name":"И.","person_surname":"Риттер","service_in_company_profession":"Механик","wage_type":"yearly","wage_value":"1900","wage_unit":"Рубль"},"210":{"source_page":"20","person_name":"А.","person_surname":"Рихтер","service_in_company_profession":"Помощник капитана","wage_type":"yearly","wage_value":"799","wage_unit":"Рубль"},"211":{"source_page":"20","person_name":"Н.","person_surname":"Рихтер","service_in_company_profession":"Механик","wage_type":"yearly","wage_value":"729","wage_unit":"Рубль"},"212":{"source_page":"20","person_name":"В.","person_surname":"Резниченко","service_in_company_profession":"Помощник капитана","wage_type":"yearly","wage_value":"1464","wage_unit":"Рубль"},"213":{"source_page":"20","person_name":"Н.","person_surname":"Рубен","service_in_company_profession":"Помощник капитана","wage_type":"yearly","wage_value":"13","wage_unit":"Рубль"},"214":{"source_page":"20","person_surname":"Реньери","service_in_company_profession":"Помощник капитана","wage_type":"yearly","wage_value":"635","wage_unit":"Рубль"},"215":{"source_page":"20","person_name":"И.","person_surname":"Рикители","service_in_company_profession":"Помощник капитана","wage_type":"yearly","wage_value":"900","wage_unit":"Рубль"},"216":{"source_page":"20","person_surname":"Райт","service_in_company_profession":"Механик","wage_type":"yearly","wage_value":"531","wage_unit":"Рубль"},"217":{"source_page":"20","person_name":"Д.","person_surname":"Риттер","service_in_company_profession":"Механик","wage_type":"yearly","wage_value":"1049","wage_unit":"Рубль"},"218":{"source_page":"20","person_name":"Дж.","person_surname":"Риттер","service_in_company_profession":"Механик","wage_type":"yearly","wage_value":"1377","wage_unit":"Рубль"},"219":{"source_page":"20","person_name":"К.","person_surname":"Рюккштюль","service_in_company_profession":"Механик","wage_type":"yearly","wage_value":"1166","wage_unit":"Рубль"},"220":{"source_page":"20","person_name":"Е.","person_surname":"Рыжов","service_in_company_profession":"Механик","wage_type":"yearly","wage_value":"468","wage_unit":"Рубль"},"221":{"source_page":"20","person_name":"Т.","person_surname":"Сосков","service_in_company_profession":"Механик","wage_type":"yearly","wage_value":"1272","wage_unit":"Рубль"},"222":{"source_page":"20","person_name":"Д.","person_surname":"Свешников","service_in_company_profession":"Капитан","wage_type":"yearly","wage_value":"2292","wage_unit":"Рубль"},"223":{"source_page":"20","person_name":"М.","person_surname":"Селистранов","service_in_company_profession":"Капитан","wage_type":"yearly","wage_value":"2263","wage_unit":"Рубль"},"224":{"source_page":"20","person_name":"С.","person_surname":"Сотири","service_in_company_profession":"Капитан","wage_type":"yearly","wage_value":"1600","wage_unit":"Рубль"},"225":{"source_page":"20","person_name":"А.","person_surname":"Сухомлин","service_in_company_profession":"Капитан","wage_type":"yearly","wage_value":"2175","wage_unit":"Рубль"},"226":{"source_page":"20","person_name":"А.","person_surname":"Степанов","service_in_company_profession":"Капитан","wage_type":"yearly","wage_value":"3111","wage_unit":"Рубль"},"227":{"source_page":"22","person_name":"И.","person_surname":"Сарычов","service_in_company_profession":"Капитан","wage_type":"yearly","wage_value":"3755","wage_unit":"Рубль"},"228":{"source_page":"22","person_name":"П.","person_surname":"Серков","service_in_company_profession":"Капитан","wage_type":"yearly","wage_value":"1631","wage_unit":"Рубль"},"229":{"source_page":"22","person_name":"П.","person_surname":"Семенов","service_in_company_profession":"Капитан","wage_type":"yearly","wage_value":"2315","wage_unit":"Рубль"},"230":{"source_page":"22","person_name":"Н.","person_surname":"Саулович","service_in_company_profession":"Помощник капитана","wage_type":"yearly","wage_value":"845","wage_unit":"Рубль"},"231":{"source_page":"22","person_name":"Ф.","person_surname":"Степанов","service_in_company_profession":"Помощник капитана","wage_type":"yearly","wage_value":"1400","wage_unit":"Рубль"},"232":{"source_page":"22","person_name":"И.","person_surname":"Слесаренко","service_in_company_profession":"Помощник капитана","wage_type":"yearly","wage_value":"366","wage_unit":"Рубль"},"233":{"source_page":"22","person_name":"М.","person_surname":"Сагайда","service_in_company_profession":"Механический ученик","wage_type":"yearly","wage_value":"195","wage_unit":"Рубль"},"234":{"source_page":"22","person_name":"Е.","person_surname":"Серебряков","service_in_company_profession":"Капитан","wage_type":"yearly","wage_value":"2155","wage_unit":"Рубль"},"235":{"source_page":"22","person_name":"Гр.","person_surname":"Собецкий","service_in_company_profession":"Механический ученик","wage_type":"yearly","wage_value":"352","wage_unit":"Рубль"},"236":{"source_page":"22","person_name":"А.","person_surname":"Соколов","service_in_company_profession":"Механический ученик","wage_type":"yearly","wage_value":"270","wage_unit":"Рубль"},"237":{"source_page":"22","person_name":"С.","person_surname":"Серафимов","service_in_company_profession":"Помощник капитана","wage_type":"yearly","wage_value":"724","wage_unit":"Рубль"},"238":{"source_page":"22","person_name":"Я.","person_surname":"Сиваков","service_in_company_profession":"Помощник капитана","wage_type":"yearly","wage_value":"333","wage_unit":"Рубль"},"239":{"source_page":"22","person_name":"П.","person_surname":"Смит","service_in_company_profession":"Механик","wage_type":"yearly","wage_value":"41","wage_unit":"Рубль"},"240":{"source_page":"22","person_name":"П.","person_surname":"Степанов","service_in_company_profession":"Помощник капитана","wage_type":"yearly","wage_value":"689","wage_unit":"Рубль"},"241":{"source_page":"22","person_name":"И.","person_surname":"Степанов","service_in_company_profession":"Помощник капитана","wage_type":"yearly","wage_value":"417","wage_unit":"Рубль"},"242":{"source_page":"22","person_surname":"Спицын","service_in_company_profession":"Капитан","wage_type":"yearly","wage_value":"500","wage_unit":"Рубль"},"243":{"source_page":"22","person_surname":"Спун","service_in_company_profession":"Помощник капитана","wage_type":"yearly","wage_value":"620","wage_unit":"Рубль"},"244":{"source_page":"22","person_name":"В.","person_surname":"Соменс","service_in_company_profession":"Механик","wage_type":"yearly","wage_value":"301","wage_unit":"Рубль"},"245":{"source_page":"24","person_surname":"Свонстон","service_in_company_profession":"Механик","wage_type":"yearly","wage_value":"205","wage_unit":"Рубль"},"246":{"source_page":"24","person_name":"А.","person_surname":"Тумилович","service_in_company_profession":"Помощник капитана","wage_type":"yearly","wage_value":"1600","wage_unit":"Рубль"},"247":{"source_page":"24","person_name":"И.","person_surname":"Тищенко","service_in_company_profession":"Помощник капитана","wage_type":"yearly","wage_value":"1475","wage_unit":"Рубль"},"248":{"source_page":"24","person_name":"Я.","person_surname":"Тетерин","service_in_company_profession":"Помощник капитана","wage_type":"yearly","wage_value":"135","wage_unit":"Рубль"},"249":{"source_page":"24","person_name":"А.","person_surname":"Тау","service_in_company_profession":"Механик","wage_type":"yearly","wage_value":"2046","wage_unit":"Рубль"},"250":{"source_page":"24","person_name":"Д.","person_surname":"Тельке","service_in_company_profession":"Механик","wage_type":"yearly","wage_value":"1600","wage_unit":"Рубль"},"251":{"source_page":"24","person_name":"А.","person_surname":"Токарев","service_in_company_profession":"Механический ученик","wage_type":"yearly","wage_value":"246","wage_unit":"Рубль"},"252":{"source_page":"24","person_name":"В.","person_surname":"Тет","service_in_company_profession":"Механик","wage_type":"yearly","wage_value":"1858","wage_unit":"Рубль"},"253":{"source_page":"24","person_name":"М.","person_surname":"Томович","service_in_company_profession":"Помощник капитана","wage_type":"yearly","wage_value":"416","wage_unit":"Рубль"},"254":{"source_page":"24","person_name":"М.","person_surname":"Фортунов","service_in_company_profession":"Помощник капитана","wage_type":"yearly","wage_value":"508","wage_unit":"Рубль"},"255":{"source_page":"24","person_name":"М.","person_surname":"Финоль","service_in_company_profession":"Механик","wage_type":"yearly","wage_value":"1507","wage_unit":"Рубль"},"256":{"source_page":"24","person_name":"К.","person_surname":"Фидион","service_in_company_profession":"Механик","wage_type":"yearly","wage_value":"649","wage_unit":"Рубль"},"257":{"source_page":"24","person_surname":"Фавье","service_in_company_profession":"Механик","wage_type":"yearly","wage_value":"733","wage_unit":"Рубль"},"258":{"source_page":"24","person_surname":"Фон-Тобель","service_in_company_profession":"Механик","wage_type":"yearly","wage_value":"705","wage_unit":"Рубль"},"259":{"source_page":"24","person_name":"Ф.","person_surname":"Христиан","service_in_company_profession":"Механик","wage_type":"yearly","wage_value":"1646","wage_unit":"Рубль"},"260":{"source_page":"24","person_name":"Л.","person_surname":"Хаколовский","service_in_company_profession":"Помощник капитана","wage_type":"yearly","wage_value":"609","wage_unit":"Рубль"},"261":{"source_page":"24","person_name":"А.","person_surname":"Ценовский","service_in_company_profession":"Механик","wage_type":"yearly","wage_value":"1558","wage_unit":"Рубль"},"262":{"source_page":"24","person_name":"С.","person_surname":"Чингрия","service_in_company_profession":"Капитан","wage_type":"yearly","wage_value":"1975","wage_unit":"Рубль"},"263":{"source_page":"24","person_surname":"Черногорчевич","service_in_company_profession":"Помощник капитана","wage_type":"yearly","wage_value":"1000","wage_unit":"Рубль"},"264":{"source_page":"24","person_surname":"Чаушанский","service_in_company_profession":"Помощник капитана","wage_type":"yearly","wage_value":"250","wage_unit":"Рубль"},"265":{"source_page":"24","person_name":"И.","person_surname":"Шестириков","service_in_company_profession":"Помощник капитана","wage_type":"yearly","wage_value":"637","wage_unit":"Рубль"},"266":{"source_page":"24","person_name":"П.","person_surname":"Шмидт","service_in_company_profession":"Капитан","wage_type":"yearly","wage_value":"3510","wage_unit":"Рубль"},"267":{"source_page":"24","person_name":"В.","person_surname":"Шульц","service_in_company_profession":"Капитан","wage_type":"yearly","wage_value":"1500","wage_unit":"Рубль"},"268":{"source_page":"26","person_name":"И.","person_surname":"Шостенко","service_in_company_profession":"Капитан","wage_type":"yearly","wage_value":"1600","wage_unit":"Рубль"},"269":{"source_page":"26","person_name":"Ф.","person_surname":"Шемизар","service_in_company_profession":"Механик","wage_type":"yearly","wage_value":"1641","wage_unit":"Рубль"},"270":{"source_page":"26","person_name":"А.","person_surname":"Шмаков","service_in_company_profession":"Помощник капитана","wage_type":"yearly","wage_value":"2011","wage_unit":"Рубль"},"271":{"source_page":"26","person_name":"А.","person_surname":"Шведов","service_in_company_profession":"Механический ученик","wage_type":"yearly","wage_value":"41","wage_unit":"Рубль"},"272":{"source_page":"26","person_name":"И.","person_surname":"Шатайлов","service_in_company_profession":"Механик","wage_type":"yearly","wage_value":"1571","wage_unit":"Рубль"},"273":{"source_page":"26","person_name":"Ф.","person_surname":"Швейцов","service_in_company_profession":"Помощник капитана","wage_type":"yearly","wage_value":"1616","wage_unit":"Рубль"},"274":{"source_page":"26","person_surname":"Шуликов","service_in_company_profession":"Помощник капитана","wage_type":"yearly","wage_value":"513","wage_unit":"Рубль"},"275":{"source_page":"26","person_name":"В.","person_surname":"Шельтинг","service_in_company_profession":"Капитан","wage_type":"yearly","wage_value":"1554","wage_unit":"Рубль"},"276":{"source_page":"26","person_name":"В.","person_surname":"Шемиот","service_in_company_profession":"Помощник капитана","wage_type":"yearly","wage_value":"708","wage_unit":"Рубль"},"277":{"source_page":"26","person_name":"Л.","person_surname":"Шервен","service_in_company_profession":"Механик","wage_type":"yearly","wage_value":"976","wage_unit":"Рубль"},"278":{"source_page":"26","person_name":"М.","person_surname":"Щербина","service_in_company_profession":"Помощник капитана","wage_type":"yearly","wage_value":"774","wage_unit":"Рубль"},"279":{"source_page":"26","person_name":"В.","person_surname":"Эрншау","service_in_company_profession":"Механик","wage_type":"yearly","wage_value":"943","wage_unit":"Рубль"},"280":{"source_page":"26","person_surname":"Энгельман","service_in_company_profession":"Помощник капитана","wage_type":"yearly","wage_value":"1392","wage_unit":"Рубль"},"281":{"source_page":"26","person_surname":"Эллиот","service_in_company_profession":"Механик","wage_type":"yearly","wage_value":"1937","wage_unit":"Рубль"},"282":{"source_page":"26","person_name":"В.","person_surname":"Яковенко","service_in_company_profession":"Помощник капитана","wage_type":"yearly","wage_value":"782","wage_unit":"Рубль"},"283":{"source_page":"26","person_name":"И.","person_surname":"Яковлев","service_in_company_profession":"Механический ученик","wage_type":"yearly","wage_value":"455","wage_unit":"Рубль"},"284":{"source_page":"26","person_name":"А.","person_surname":"Языков","service_in_company_profession":"Капитан","wage_type":"yearly","wage_value":"2287","wage_unit":"Рубль"},"285":{"source_page":"26","person_name":"Ф.","person_surname":"Якунин","service_in_company_profession":"Механический ученик","wage_type":"yearly","wage_value":"131","wage_unit":"Рубль"},"286":{"source_page":"26","person_surname":"Язерский","service_in_company_profession":"Механик","wage_type":"yearly","wage_value":"1080","wage_unit":"Рубль"},"287":{},"288":{},"289":{},"290":{}}}}]}